figure_scale/__init__.py
figure_scale/_version.py
figure_scale/core.py
figure_scale/py.typed
figure_scale/unit_conversion.py
figure_scale/utils/singleton.py
figure_scale-0.1.0.dist-info/METADATA
figure_scale-0.1.0.dist-info/WHEEL
figure_scale-0.1.0.dist-info/licenses/LICENSE
figure_scale-0.1.0.dist-info/RECORD
