Metadata-Version: 2.4
Name: figure-scale
Version: 0.1.0
Summary: Make Matplotlib figures with the correct scale.
Project-URL: Source, https://github.com/fschuch/figure-scale
Project-URL: Tracker, https://github.com/fschuch/figure-scale/issues
Project-URL: Changelog, https://github.com/fschuch/figure-scale/releases
Author-email: fschuch <me@fschuch.com>
License-Expression: MIT
License-File: LICENSE
Classifier: Development Status :: 5 - Production/Stable
Classifier: Framework :: Matplotlib
Classifier: Intended Audience :: Education
Classifier: Intended Audience :: Science/Research
Classifier: License :: OSI Approved :: MIT License
Classifier: Operating System :: OS Independent
Classifier: Programming Language :: Python
Classifier: Programming Language :: Python :: 3
Classifier: Programming Language :: Python :: 3.9
Classifier: Programming Language :: Python :: 3.10
Classifier: Programming Language :: Python :: 3.11
Classifier: Programming Language :: Python :: 3.12
Classifier: Programming Language :: Python :: 3.13
Classifier: Topic :: Scientific/Engineering
Classifier: Topic :: Scientific/Engineering :: Visualization
Requires-Python: >=3.9
Requires-Dist: matplotlib>=3.2.0
Provides-Extra: docs
Requires-Dist: docutils==0.21.2; extra == 'docs'
Requires-Dist: jupyter-book==1.0.4.post1; extra == 'docs'
Requires-Dist: sphinx-autobuild==2024.10.3; extra == 'docs'
Requires-Dist: sphinx-github-changelog==1.7.1; extra == 'docs'
Requires-Dist: sphinx==7.4.7; extra == 'docs'
Provides-Extra: tests
Requires-Dist: coverage[toml]>=7.5.3; extra == 'tests'
Requires-Dist: pint>=0.15.0; extra == 'tests'
Requires-Dist: pre-commit>=3.5.0; extra == 'tests'
Requires-Dist: pytest-cov>=5.0.0; extra == 'tests'
Requires-Dist: pytest>=8.2.2; extra == 'tests'
Provides-Extra: tests-extra
Requires-Dist: pytest-randomly==3.16.0; extra == 'tests-extra'
Requires-Dist: pytest-rerunfailures==15.1; extra == 'tests-extra'
Requires-Dist: pytest-xdist==3.8.0; extra == 'tests-extra'
